apisix_client/__init__.py
apisix_client/base_models.py
apisix_client/client.py
apisix_client/protocols.py
apisix_client/py.typed
apisix_client/version.py
apisix_client/common/__init__.py
apisix_client/common/converter.py
apisix_client/common/models.py
apisix_client/common/utils.py
apisix_client/consumer/__init__.py
apisix_client/consumer/client.py
apisix_client/consumer/models.py
apisix_client/credential/__init__.py
apisix_client/credential/client.py
apisix_client/credential/models.py
apisix_client/global_rule/__init__.py
apisix_client/global_rule/client.py
apisix_client/global_rule/models.py
apisix_client/plugin/__init__.py
apisix_client/plugin/client.py
apisix_client/plugin/models/__init__.py
apisix_client/plugin/models/base.py
apisix_client/plugin/models/key_auth.py
apisix_client/plugin/models/limit_count.py
apisix_client/plugin/models/observability/__init__.py
apisix_client/plugin/models/observability/loggers/__init__.py
apisix_client/plugin/models/observability/loggers/clickhouse.py
apisix_client/route/__init__.py
apisix_client/route/client.py
apisix_client/route/models.py
apisix_client/secret/__init__.py
apisix_client/secret/client.py
apisix_client/secret/models.py
apisix_client/service/__init__.py
apisix_client/service/client.py
apisix_client/service/models.py
apisix_client/ssl/__init__.py
apisix_client/ssl/client.py
apisix_client/ssl/models.py
apisix_client/upstream/__init__.py
apisix_client/upstream/client.py
apisix_client/upstream/models.py
apisix_client-0.5.0.dist-info/licenses/LICENSE
apisix_client-0.5.0.dist-info/METADATA
apisix_client-0.5.0.dist-info/WHEEL
apisix_client-0.5.0.dist-info/top_level.txt
apisix_client-0.5.0.dist-info/RECORD
