Metadata-Version: 2.4
Name: apisix-client
Version: 0.5.0
Summary: Python sdk for apisix admin api
Author-email: Dominik Tkacik <tkacik38@gmail.com>, Jan Tkacik <jan.tkacik@gmail.com>, info@neuronum.sk
Maintainer-email: Dominik Tkacik <tkacik38@gmail.com>, Jan Tkacik <jan.tkacik@gmail.com>
License-Expression: MIT
Project-URL: Homepage, https://github.com/NeuronumOfficial/apisix-client
Project-URL: Documentation, https://github.com/NeuronumOfficial/apisix-client
Project-URL: Repository, https://github.com/NeuronumOfficial/apisix-client
Project-URL: Bug Tracker, https://github.com/NeuronumOfficial/apisix-client/issues
Keywords: apisix,sdk,neuronum
Classifier: Intended Audience :: Developers
Classifier: Development Status :: 2 - Pre-Alpha
Classifier: Programming Language :: Python
Classifier: Operating System :: OS Independent
Classifier: Operating System :: POSIX
Classifier: Operating System :: MacOS
Classifier: Operating System :: POSIX :: Linux
Classifier: Operating System :: Microsoft :: Windows
Classifier: Topic :: Software Development :: Libraries :: Python Modules
Classifier: Typing :: Typed
Requires-Python: >=3.9
License-File: LICENSE
Requires-Dist: httpx<1.0,>=0.27
Requires-Dist: pyhumps<4.0,>=3.8
Requires-Dist: attrs<25.0,>=24.3
Requires-Dist: cattrs<25.0,>=24.1
Provides-Extra: dev
Requires-Dist: black>=25.0; extra == "dev"
Requires-Dist: ruff>=0.12; extra == "dev"
Requires-Dist: isort>=6.0; extra == "dev"
Dynamic: license-file
